{"config":{"output_file":null,"full_docs":false,"pub_only":false,"reachable_only":false,"distro_crate":false,"signatures":false,"borrow_data":false},"version":"0.18.2","compilation":{"directory":[69,58,92,114,117,115,116,92,109,111,100,95,108,101,97,114,110],"program":"C:\\Users\\RWX\\.rustup\\toolchains\\stable-x86_64-pc-windows-msvc\\bin\\rls.exe","arguments":[],"output":[101,58,92,114,117,115,116,92,116,101,115,116,95,99,114,97,116,101,92,116,97,114,103,101,116,92,114,108,115,92,100,101,98,117,103,92,100,101,112,115,92,108,105,98,109,111,100,95,108,101,97,114,110,45,99,57,57,54,55,50,50,99,50,102,101,54,52,55,57,49,46,114,109,101,116,97]},"prelude":{"crate_id":{"name":"mod_learn","disambiguator":[331805129039116963,5938341254020578417]},"crate_root":"E:\\rust\\mod_learn\\src","external_crates":[{"file_name":"E:\\rust\\mod_learn\\src\\lib.rs","num":1,"id":{"name":"std","disambiguator":[6497413695257409113,8363414768885484514]}},{"file_name":"E:\\rust\\mod_learn\\src\\lib.rs","num":2,"id":{"name":"core","disambiguator":[18058147969333450893,13268649681863949094]}},{"file_name":"E:\\rust\\mod_learn\\src\\lib.rs","num":3,"id":{"name":"compiler_builtins","disambiguator":[11952756852394341397,15947907305756316424]}},{"file_name":"E:\\rust\\mod_learn\\src\\lib.rs","num":4,"id":{"name":"rustc_std_workspace_core","disambiguator":[3630013859029208871,3806232699279168156]}},{"file_name":"E:\\rust\\mod_learn\\src\\lib.rs","num":5,"id":{"name":"alloc","disambiguator":[12834222563671543008,8524540247763871862]}},{"file_name":"E:\\rust\\mod_learn\\src\\lib.rs","num":6,"id":{"name":"libc","disambiguator":[18371008013690111012,4867424062236140066]}},{"file_name":"E:\\rust\\mod_learn\\src\\lib.rs","num":7,"id":{"name":"unwind","disambiguator":[438167776779553502,12488629561743155773]}},{"file_name":"E:\\rust\\mod_learn\\src\\lib.rs","num":8,"id":{"name":"rustc_demangle","disambiguator":[1419137526044370392,14298439468463405642]}},{"file_name":"E:\\rust\\mod_learn\\src\\lib.rs","num":9,"id":{"name":"panic_unwind","disambiguator":[8847763227328938631,1920228220721921728]}}],"span":{"file_name":[69,58,92,114,117,115,116,92,109,111,100,95,108,101,97,114,110,92,115,114,99,92,108,105,98,46,114,115],"byte_start":0,"byte_end":52,"line_start":1,"line_end":3,"column_start":1,"column_end":16}},"imports":[],"defs":[{"kind":"Mod","id":{"krate":0,"index":0},"span":{"file_name":[69,58,92,114,117,115,116,92,109,111,100,95,108,101,97,114,110,92,115,114,99,92,108,105,98,46,114,115],"byte_start":0,"byte_end":52,"line_start":1,"line_end":3,"column_start":1,"column_end":16},"name":"","qualname":"::","value":"E:\\rust\\mod_learn\\src\\lib.rs","parent":null,"children":[{"krate":0,"index":2},{"krate":0,"index":4},{"krate":0,"index":6},{"krate":0,"index":16},{"krate":0,"index":26}],"decl_id":null,"docs":"","sig":null,"attributes":[]},{"kind":"Mod","id":{"krate":0,"index":6},"span":{"file_name":[69,58,92,114,117,115,116,92,109,111,100,95,108,101,97,114,110,92,115,114,99,92,101,110,103,108,105,115,104,92,109,111,100,46,114,115],"byte_start":0,"byte_end":0,"line_start":1,"line_end":1,"column_start":1,"column_end":1},"name":"english","qualname":"::english","value":"E:\\rust\\mod_learn\\src\\english\\mod.rs","parent":null,"children":[{"krate":0,"index":8},{"krate":0,"index":12}],"decl_id":null,"docs":"","sig":null,"attributes":[]},{"kind":"Mod","id":{"krate":0,"index":8},"span":{"file_name":[69,58,92,114,117,115,116,92,109,111,100,95,108,101,97,114,110,92,115,114,99,92,101,110,103,108,105,115,104,92,103,114,101,101,116,105,110,103,115,46,114,115],"byte_start":0,"byte_end":0,"line_start":1,"line_end":1,"column_start":1,"column_end":1},"name":"greetings","qualname":"::english::greetings","value":"E:\\rust\\mod_learn\\src\\english\\greetings.rs","parent":null,"children":[{"krate":0,"index":10}],"decl_id":null,"docs":"","sig":null,"attributes":[]},{"kind":"Function","id":{"krate":0,"index":10},"span":{"file_name":[69,58,92,114,117,115,116,92,109,111,100,95,108,101,97,114,110,92,115,114,99,92,101,110,103,108,105,115,104,92,103,114,101,101,116,105,110,103,115,46,114,115],"byte_start":99,"byte_end":104,"line_start":1,"line_end":1,"column_start":8,"column_end":13},"name":"hello","qualname":"::english::greetings::hello","value":"fn () -> String","parent":null,"children":[],"decl_id":null,"docs":"","sig":null,"attributes":[]},{"kind":"Mod","id":{"krate":0,"index":12},"span":{"file_name":[69,58,92,114,117,115,116,92,109,111,100,95,108,101,97,114,110,92,115,114,99,92,101,110,103,108,105,115,104,92,102,97,114,101,119,101,108,108,115,46,114,115],"byte_start":0,"byte_end":0,"line_start":1,"line_end":1,"column_start":1,"column_end":1},"name":"farewells","qualname":"::english::farewells","value":"E:\\rust\\mod_learn\\src\\english\\farewells.rs","parent":null,"children":[{"krate":0,"index":14}],"decl_id":null,"docs":"","sig":null,"attributes":[]},{"kind":"Function","id":{"krate":0,"index":14},"span":{"file_name":[69,58,92,114,117,115,116,92,109,111,100,95,108,101,97,114,110,92,115,114,99,92,101,110,103,108,105,115,104,92,102,97,114,101,119,101,108,108,115,46,114,115],"byte_start":156,"byte_end":163,"line_start":1,"line_end":1,"column_start":9,"column_end":16},"name":"goodbye","qualname":"::english::farewells::goodbye","value":"fn () -> String","parent":null,"children":[],"decl_id":null,"docs":"","sig":null,"attributes":[]},{"kind":"Mod","id":{"krate":0,"index":16},"span":{"file_name":[69,58,92,114,117,115,116,92,109,111,100,95,108,101,97,114,110,92,115,114,99,92,106,97,112,97,110,101,115,101,92,109,111,100,46,114,115],"byte_start":0,"byte_end":0,"line_start":1,"line_end":1,"column_start":1,"column_end":1},"name":"japanese","qualname":"::japanese","value":"E:\\rust\\mod_learn\\src\\japanese\\mod.rs","parent":null,"children":[{"krate":0,"index":18},{"krate":0,"index":22}],"decl_id":null,"docs":"","sig":null,"attributes":[]},{"kind":"Mod","id":{"krate":0,"index":18},"span":{"file_name":[69,58,92,114,117,115,116,92,109,111,100,95,108,101,97,114,110,92,115,114,99,92,106,97,112,97,110,101,115,101,92,103,114,101,101,116,105,110,103,115,46,114,115],"byte_start":0,"byte_end":0,"line_start":1,"line_end":1,"column_start":1,"column_end":1},"name":"greetings","qualname":"::japanese::greetings","value":"E:\\rust\\mod_learn\\src\\japanese\\greetings.rs","parent":null,"children":[{"krate":0,"index":20}],"decl_id":null,"docs":"","sig":null,"attributes":[]},{"kind":"Function","id":{"krate":0,"index":20},"span":{"file_name":[69,58,92,114,117,115,116,92,109,111,100,95,108,101,97,114,110,92,115,114,99,92,106,97,112,97,110,101,115,101,92,103,114,101,101,116,105,110,103,115,46,114,115],"byte_start":262,"byte_end":267,"line_start":1,"line_end":1,"column_start":8,"column_end":13},"name":"hello","qualname":"::japanese::greetings::hello","value":"fn () -> String","parent":null,"children":[],"decl_id":null,"docs":"","sig":null,"attributes":[]},{"kind":"Mod","id":{"krate":0,"index":22},"span":{"file_name":[69,58,92,114,117,115,116,92,109,111,100,95,108,101,97,114,110,92,115,114,99,92,106,97,112,97,110,101,115,101,92,102,97,114,101,119,101,108,108,115,46,114,115],"byte_start":0,"byte_end":0,"line_start":1,"line_end":1,"column_start":1,"column_end":1},"name":"farewells","qualname":"::japanese::farewells","value":"E:\\rust\\mod_learn\\src\\japanese\\farewells.rs","parent":null,"children":[{"krate":0,"index":24}],"decl_id":null,"docs":"","sig":null,"attributes":[]},{"kind":"Function","id":{"krate":0,"index":24},"span":{"file_name":[69,58,92,114,117,115,116,92,109,111,100,95,108,101,97,114,110,92,115,114,99,92,106,97,112,97,110,101,115,101,92,102,97,114,101,119,101,108,108,115,46,114,115],"byte_start":332,"byte_end":339,"line_start":1,"line_end":1,"column_start":9,"column_end":16},"name":"goodbye","qualname":"::japanese::farewells::goodbye","value":"fn () -> String","parent":null,"children":[],"decl_id":null,"docs":"","sig":null,"attributes":[]},{"kind":"Mod","id":{"krate":0,"index":26},"span":{"file_name":[69,58,92,114,117,115,116,92,109,111,100,95,108,101,97,114,110,92,115,114,99,92,109,121,95,108,105,98,46,114,115],"byte_start":0,"byte_end":0,"line_start":1,"line_end":1,"column_start":1,"column_end":1},"name":"my_lib","qualname":"::my_lib","value":"E:\\rust\\mod_learn\\src\\my_lib.rs","parent":null,"children":[{"krate":0,"index":28}],"decl_id":null,"docs":"","sig":null,"attributes":[]},{"kind":"Mod","id":{"krate":0,"index":28},"span":{"file_name":[69,58,92,114,117,115,116,92,109,111,100,95,108,101,97,114,110,92,115,114,99,92,109,121,95,108,105,98,92,97,99,116,95,109,111,100,46,114,115],"byte_start":0,"byte_end":0,"line_start":1,"line_end":1,"column_start":1,"column_end":1},"name":"act_mod","qualname":"::my_lib::act_mod","value":"E:\\rust\\mod_learn\\src\\my_lib\\act_mod.rs","parent":null,"children":[{"krate":0,"index":30}],"decl_id":null,"docs":"","sig":null,"attributes":[]},{"kind":"Function","id":{"krate":0,"index":30},"span":{"file_name":[69,58,92,114,117,115,116,92,109,111,100,95,108,101,97,114,110,92,115,114,99,92,109,121,95,108,105,98,92,97,99,116,95,109,111,100,46,114,115],"byte_start":420,"byte_end":423,"line_start":1,"line_end":1,"column_start":8,"column_end":11},"name":"run","qualname":"::my_lib::act_mod::run","value":"fn () -> ()","parent":null,"children":[],"decl_id":null,"docs":"","sig":null,"attributes":[]}],"impls":[],"refs":[{"kind":"Mod","span":{"file_name":[69,58,92,114,117,115,116,92,109,111,100,95,108,101,97,114,110,92,115,114,99,92,108,105,98,46,114,115],"byte_start":8,"byte_end":15,"line_start":1,"line_end":1,"column_start":9,"column_end":16},"ref_id":{"krate":0,"index":6}},{"kind":"Mod","span":{"file_name":[69,58,92,114,117,115,116,92,109,111,100,95,108,101,97,114,110,92,115,114,99,92,101,110,103,108,105,115,104,92,109,111,100,46,114,115],"byte_start":61,"byte_end":70,"line_start":1,"line_end":1,"column_start":9,"column_end":18},"ref_id":{"krate":0,"index":8}},{"kind":"Type","span":{"file_name":[69,58,92,114,117,115,116,92,109,111,100,95,108,101,97,114,110,92,115,114,99,92,101,110,103,108,105,115,104,92,103,114,101,101,116,105,110,103,115,46,114,115],"byte_start":110,"byte_end":116,"line_start":1,"line_end":1,"column_start":19,"column_end":25},"ref_id":{"krate":5,"index":5512}},{"kind":"Function","span":{"file_name":[69,58,92,114,117,115,116,92,109,111,100,95,108,101,97,114,110,92,115,114,99,92,101,110,103,108,105,115,104,92,103,114,101,101,116,105,110,103,115,46,114,115],"byte_start":133,"byte_end":142,"line_start":2,"line_end":2,"column_start":14,"column_end":23},"ref_id":{"krate":5,"index":4320}},{"kind":"Mod","span":{"file_name":[69,58,92,114,117,115,116,92,109,111,100,95,108,101,97,114,110,92,115,114,99,92,101,110,103,108,105,115,104,92,109,111,100,46,114,115],"byte_start":81,"byte_end":90,"line_start":2,"line_end":2,"column_start":9,"column_end":18},"ref_id":{"krate":0,"index":12}},{"kind":"Type","span":{"file_name":[69,58,92,114,117,115,116,92,109,111,100,95,108,101,97,114,110,92,115,114,99,92,101,110,103,108,105,115,104,92,102,97,114,101,119,101,108,108,115,46,114,115],"byte_start":169,"byte_end":175,"line_start":1,"line_end":1,"column_start":22,"column_end":28},"ref_id":{"krate":5,"index":5512}},{"kind":"Function","span":{"file_name":[69,58,92,114,117,115,116,92,109,111,100,95,108,101,97,114,110,92,115,114,99,92,101,110,103,108,105,115,104,92,102,97,114,101,119,101,108,108,115,46,114,115],"byte_start":194,"byte_end":203,"line_start":2,"line_end":2,"column_start":16,"column_end":25},"ref_id":{"krate":5,"index":4320}},{"kind":"Mod","span":{"file_name":[69,58,92,114,117,115,116,92,109,111,100,95,108,101,97,114,110,92,115,114,99,92,108,105,98,46,114,115],"byte_start":26,"byte_end":34,"line_start":2,"line_end":2,"column_start":9,"column_end":17},"ref_id":{"krate":0,"index":16}},{"kind":"Mod","span":{"file_name":[69,58,92,114,117,115,116,92,109,111,100,95,108,101,97,114,110,92,115,114,99,92,106,97,112,97,110,101,115,101,92,109,111,100,46,114,115],"byte_start":222,"byte_end":231,"line_start":1,"line_end":1,"column_start":10,"column_end":19},"ref_id":{"krate":0,"index":18}},{"kind":"Type","span":{"file_name":[69,58,92,114,117,115,116,92,109,111,100,95,108,101,97,114,110,92,115,114,99,92,106,97,112,97,110,101,115,101,92,103,114,101,101,116,105,110,103,115,46,114,115],"byte_start":273,"byte_end":279,"line_start":1,"line_end":1,"column_start":19,"column_end":25},"ref_id":{"krate":5,"index":5512}},{"kind":"Function","span":{"file_name":[69,58,92,114,117,115,116,92,109,111,100,95,108,101,97,114,110,92,115,114,99,92,106,97,112,97,110,101,115,101,92,103,114,101,101,116,105,110,103,115,46,114,115],"byte_start":305,"byte_end":314,"line_start":2,"line_end":2,"column_start":13,"column_end":22},"ref_id":{"krate":5,"index":4320}},{"kind":"Mod","span":{"file_name":[69,58,92,114,117,115,116,92,109,111,100,95,108,101,97,114,110,92,115,114,99,92,106,97,112,97,110,101,115,101,92,109,111,100,46,114,115],"byte_start":244,"byte_end":253,"line_start":2,"line_end":2,"column_start":11,"column_end":20},"ref_id":{"krate":0,"index":22}},{"kind":"Type","span":{"file_name":[69,58,92,114,117,115,116,92,109,111,100,95,108,101,97,114,110,92,115,114,99,92,106,97,112,97,110,101,115,101,92,102,97,114,101,119,101,108,108,115,46,114,115],"byte_start":345,"byte_end":351,"line_start":1,"line_end":1,"column_start":22,"column_end":28},"ref_id":{"krate":5,"index":5512}},{"kind":"Function","span":{"file_name":[69,58,92,114,117,115,116,92,109,111,100,95,108,101,97,114,110,92,115,114,99,92,106,97,112,97,110,101,115,101,92,102,97,114,101,119,101,108,108,115,46,114,115],"byte_start":377,"byte_end":386,"line_start":2,"line_end":2,"column_start":13,"column_end":22},"ref_id":{"krate":5,"index":4320}},{"kind":"Mod","span":{"file_name":[69,58,92,114,117,115,116,92,109,111,100,95,108,101,97,114,110,92,115,114,99,92,108,105,98,46,114,115],"byte_start":45,"byte_end":51,"line_start":3,"line_end":3,"column_start":9,"column_end":15},"ref_id":{"krate":0,"index":26}},{"kind":"Mod","span":{"file_name":[69,58,92,114,117,115,116,92,109,111,100,95,108,101,97,114,110,92,115,114,99,92,109,121,95,108,105,98,46,114,115],"byte_start":404,"byte_end":411,"line_start":1,"line_end":1,"column_start":9,"column_end":16},"ref_id":{"krate":0,"index":28}}],"macro_refs":[],"relations":[]}